mitransient/__init__.py
mitransient/nlos.py
mitransient/polarized_visualization.py
mitransient/unpolarized_visualization.py
mitransient/utils.py
mitransient/version.py
mitransient/visualization.py
mitransient/emitters/__init__.py
mitransient/emitters/angulararea.py
mitransient/films/__init__.py
mitransient/films/fourier_hdr_film.py
mitransient/films/phasor_hdr_film.py
mitransient/films/transient_hdr_film.py
mitransient/integrators/__init__.py
mitransient/integrators/common.py
mitransient/integrators/transient_prb_volpath.py
mitransient/integrators/transient_prbvolpath.py
mitransient/integrators/transientnlospath.py
mitransient/integrators/transientpath.py
mitransient/render/__init__.py
mitransient/render/fourier_image_block.py
mitransient/render/phasor_image_block.py
mitransient/render/transient_block.py
mitransient/render/transient_image_block.py
mitransient/sensors/__init__.py
mitransient/sensors/nloscapturemeter.py
mitransient/sensors/nlossensor.py
mitransient-1.2.0.dist-info/METADATA
mitransient-1.2.0.dist-info/WHEEL
mitransient-1.2.0.dist-info/top_level.txt
mitransient-1.2.0.dist-info/RECORD
