Metadata-Version: 2.1
Name: mitransient
Version: 1.2.0
Summary: Transient rendering extensions for Mitsuba 3
Home-page: https://github.com/diegoroyo/mitransient
Author: Diego Royo, Miguel Crespo, Jorge García
Author-email: droyo@unizar.es
License: BSD
Requires-Python: >=3.8
Requires-Dist: mitsuba<3.8.0,>=3.6.0
Provides-Extra: recommended
Requires-Dist: numpy; extra == "recommended"
Requires-Dist: matplotlib; extra == "recommended"
Requires-Dist: opencv-python; extra == "recommended"
